ycpk/__init__.py
ycpk/main.py
ycpk/calib_camera/__init__.py
ycpk/calib_camera/calibrator.py
ycpk/calib_camera/main.py
ycpk/fusion/__init__.py
ycpk/fusion/fusion.py
ycpk/fusion/main.py
ycpk/gif_generator/__init__.py
ycpk/gif_generator/main.py
ycpk/read_sensing/__init__.py
ycpk/read_sensing/main.py
ycpk/read_sensing/parse_result.py
ycpk/read_sensing/sensing_reader.py
ycpk/slice/__init__.py
ycpk/slice/main.py
ycpk/slice/ros_dataset.py
ycpk/slice/slice.py
ycpk/tools/__init__.py
ycpk/tools/data_collection/__init__.py
ycpk/tools/data_collection/data_recorder.py
ycpk/tools/data_collection/main.py
ycpk/tools/data_collection/parse_config.py
ycpk/tools/data_collection/ros_dataset.py
ycpk/tools/data_collection/utils.py
ycpk/tools/ros_visualizer/__init__.py
ycpk/tools/ros_visualizer/main.py
ycpk/voc2coco/__init__.py
ycpk/voc2coco/main.py
ycpk-0.0.1.dist-info/LICENSE
ycpk-0.0.1.dist-info/METADATA
ycpk-0.0.1.dist-info/WHEEL
ycpk-0.0.1.dist-info/entry_points.txt
ycpk-0.0.1.dist-info/top_level.txt
ycpk-0.0.1.dist-info/RECORD
