Metadata-Version: 2.1
Name: ycpk
Version: 0.0.1
Summary: yun chuang perception kit
Home-page: UNKNOWN
Author: windzu
Author-email: windzu1@gmail.com
License: MIT license
Keywords: adas deeplearning
Platform: UNKNOWN
Classifier: Development Status :: 3 - Alpha
Classifier: Intended Audience :: Developers
Classifier: License :: OSI Approved :: MIT License
Classifier: Natural Language :: English
Classifier: Programming Language :: Python :: 3
Classifier: Programming Language :: Python :: 3.6
Classifier: Programming Language :: Python :: 3.7
Classifier: Programming Language :: Python :: 3.8
Requires-Python: >=3.6
Requires-Dist: imageio (==2.21.1)
Requires-Dist: numpy
Requires-Dist: opencv-python
Requires-Dist: pyyaml
Requires-Dist: rich
Requires-Dist: rospkg
Requires-Dist: wind-pypcd
